__init__.py
programmify/__init__.py
programmify/favicon.ico
programmify/programmify.py
programmify/subprocess_program.py
programmify-0.0.8.dist-info/LICENSE
programmify-0.0.8.dist-info/METADATA
programmify-0.0.8.dist-info/WHEEL
programmify-0.0.8.dist-info/entry_points.txt
programmify-0.0.8.dist-info/top_level.txt
programmify-0.0.8.dist-info/RECORD
