Metadata-Version: 2.1
Name: programmify
Version: 0.0.8
Summary: Quickly make a windows executable with a system tray icon and an configurable (read empty) PyQT5 window
Author-email: Torin Halsted <modularizer@gmail.com>
License: This is free and unencumbered software released into the public domain.
Project-URL: Homepage, https://github.com/modularizer/programmify
Keywords: program,app,icon,system tray,pyqt5,windows,executable,pyinstaller
Classifier: Programming Language :: Python :: 3
Classifier: Operating System :: OS Independent
Requires-Python: >=3.10
License-File: LICENSE
Requires-Dist: pyqt5
Requires-Dist: setproctitle
Requires-Dist: Pillow
Requires-Dist: pyinstaller
Requires-Dist: PyYAML
